file_reader_mcp/__init__.py
file_reader_mcp/server.py
file_reader_mcp-0.1.0.dist-info/METADATA
file_reader_mcp-0.1.0.dist-info/WHEEL
file_reader_mcp-0.1.0.dist-info/entry_points.txt
file_reader_mcp-0.1.0.dist-info/RECORD
