Metadata-Version: 2.4
Name: file-reader-mcp
Version: 0.1.0
Summary: MCP Server for file reading
Requires-Dist: mcp
